htm2md/__init__.py
htm2md/const.py
htm2md/parser.py
htm2md/state.py
htm2md/tag.py
htm2md-0.1.0.dist-info/LICENSE
htm2md-0.1.0.dist-info/WHEEL
htm2md-0.1.0.dist-info/METADATA
htm2md-0.1.0.dist-info/RECORD
